{
  "meta": {
    "outputLanguage": "korean",
    "assignmentType": "essay",
    "studentLevel": {
      "schoolStage": "elementary",
      "proficiency": "middle"
    },
    "generatedAt": "2026-04-05T00:00:00Z",
    "promptFiles": [
      "prompts/role.txt",
      "prompts/common-instructions.txt",
      "prompts/language/korean.txt",
      "prompts/levels/elementary.txt",
      "prompts/levels/proficiency-middle.txt",
      "prompts/assignment-types/essay.txt",
      "prompts/evaluation/base.txt",
      "prompts/evaluation/overall.txt",
      "prompts/evaluation/categories.txt",
      "prompts/feedback/base.txt",
      "prompts/feedback/overall.txt",
      "prompts/feedback/categories.txt",
      "prompts/feedback/examples.txt",
      "prompts/feedback/strengths.txt",
      "prompts/feedback/areas-to-improve.txt",
      "prompts/output/detailed-improvements.txt",
      "prompts/output/structured-output.txt"
    ]
  },
  "improvements": {
    "summary": "이 글은 책의 주요 내용을 순서대로 잘 떠올려 답했고, 사건의 흐름도 대체로 전달되었습니다. 다음 단계에서는 동사 표현, 관사, 시제, 그리고 문장 연결을 조금만 더 정확하게 쓰면 훨씬 더 자연스럽고 읽기 쉬운 글이 됩니다.",
    "detailedItems": [
      {
        "title": "pay attention 표현 쓰기",
        "original": "Finlay didn't attention to the teacher",
        "revised": "Finlay was not paying attention to the teacher",
        "rationale": "영어에서는 attention을 동사처럼 쓰지 않고 pay attention to라는 표현으로 씁니다. 그래서 didn't attention보다 was not paying attention이 자연스럽습니다.",
        "tip": "attention이 나오면 pay attention to를 한 덩어리 표현으로 외워 보세요."
      },
      {
        "title": "셀 수 있는 명사 앞에 a 쓰기",
        "original": "he brought real dog",
        "revised": "he brought a real dog",
        "rationale": "dog처럼 셀 수 있는 단수 명사 앞에는 보통 a 또는 the가 필요합니다. 여기서는 처음 나오는 강아지이므로 a가 알맞습니다.",
        "tip": "단수 명사 하나를 말할 때는 a/an/the가 필요한지 먼저 확인해 보세요."
      },
      {
        "title": "색깔 표현 바로 쓰기",
        "original": "he painted his mask to red",
        "revised": "he painted his mask red",
        "rationale": "paint + 목적어 + 색깔 형태로 많이 씁니다. 그래서 painted his mask red가 자연스럽고 to는 넣지 않습니다.",
        "tip": "painted it blue/red처럼 색깔은 바로 뒤에 붙여 쓰는 연습을 해 보세요."
      },
      {
        "title": "액체가 흘러들어갈 때 spilled into 쓰기",
        "original": "the red paint filled into the water tank",
        "revised": "the red paint spilled into the water tank",
        "rationale": "paint가 흘러 들어간 상황에서는 filled into보다 spilled into가 의미에 더 정확합니다.",
        "tip": "물감, 물, 주스처럼 액체가 쏟아지면 spill/spilled를 떠올려 보세요."
      },
      {
        "title": "진행 중이던 상황은 were practicing",
        "original": "they practiced the play",
        "revised": "they were practicing the play",
        "rationale": "이야기 속에서 그때 진행 중이던 장면을 말할 때는 과거진행형 were practicing이 더 자연스럽습니다.",
        "tip": "이야기 장면을 설명할 때 was/were + ing를 써 보면 더 생생해집니다."
      },
      {
        "title": "fish의 복수형 쓰기",
        "original": "all fishes",
        "revised": "all the fish",
        "rationale": "보통 물고기의 복수는 fishes보다 fish를 더 자연스럽게 씁니다. 그래서 all the fish가 알맞습니다.",
        "tip": "여러 마리 물고기를 말할 때는 먼저 fish를 기본형으로 떠올려 보세요."
      }
    ]
  },
  "evaluation": {
    "overallGrade": "B",
    "overallEvaluation": "질문에 모두 답하면서 이야기의 핵심 사건과 결말을 잘 전달했습니다. 문법과 표현 오류는 여러 곳에서 보이지만, 초등 수준에서는 의미 전달이 비교적 분명한 편입니다. 문장을 조금 더 정확하게 고치면 완성도가 크게 올라갈 글입니다.",
    "categories": [
      {
        "key": "taskCompletion",
        "label": "과제 수행 및 주제 적합성",
        "grade": "A",
        "summary": "모든 질문에 빠짐없이 답했고, 책의 주인공·사건·배경·이유·결말을 모두 다루었습니다."
      },
      {
        "key": "meaningDelivery",
        "label": "의미 전달과 내용 이해",
        "grade": "B",
        "summary": "전하고 싶은 내용은 대부분 이해할 수 있고, 사건의 원인과 결과도 대체로 드러납니다. 다만 몇몇 표현이 부자연스러워 읽는 사람이 잠시 멈추게 됩니다."
      },
      {
        "key": "structure",
        "label": "구조와 흐름",
        "grade": "B",
        "summary": "질문 순서에 맞춰 내용을 정리해서 흐름을 따라가기 쉽습니다. 하지만 긴 문장을 나누고 연결어를 더 자연스럽게 쓰면 더 매끄러워집니다."
      },
      {
        "key": "vocabularyExpression",
        "label": "어휘와 표현",
        "grade": "C",
        "summary": "기본 어휘로 필요한 내용을 표현하려는 시도는 좋았습니다. 그러나 pay attention, spilled into 같은 더 정확한 표현이 필요합니다."
      },
      {
        "key": "grammarAccuracy",
        "label": "문법 정확성",
        "grade": "C",
        "summary": "관사, 시제, 동사 표현, 복수형 등에서 오류가 여러 번 나타났습니다. 그래도 핵심 의미는 대부분 전달되었습니다."
      }
    ]
  },
  "feedback": {
    "overallFeedback": "이야기의 중요한 내용을 잘 기억해서 끝까지 답한 점이 좋습니다. 이제는 문장을 길게 한 번에 쓰기보다, 정확한 동사 표현과 시제를 하나씩 점검하면서 쓰면 훨씬 더 자연스러운 영어가 됩니다.",
    "categories": [
      {
        "key": "taskCompletion",
        "label": "과제 수행 및 주제 적합성",
        "feedback": "모든 질문에 답해서 과제를 성실하게 완성했습니다. 내용도 책 이야기와 잘 맞습니다.",
        "example": "예: 주인공, 주요 사건, 결말을 모두 넣은 점이 좋습니다."
      },
      {
        "key": "meaningDelivery",
        "label": "의미 전달과 내용 이해",
        "feedback": "전체 줄거리는 잘 전달됩니다. 원인과 결과를 더 분명하게 나누면 뜻이 더 잘 보입니다.",
        "example": "예: \"the red paint spilled into the water tank, so the dog barked to save the fish.\"처럼 쓰면 더 분명합니다."
      },
      {
        "key": "structure",
        "label": "구조와 흐름",
        "feedback": "사건 순서는 잘 지켰습니다. 긴 문장은 두 문장으로 나누면 읽기 쉬워집니다.",
        "example": "예: \"The dog bit his mask. Then he painted his mask red.\"처럼 나눌 수 있습니다."
      },
      {
        "key": "vocabularyExpression",
        "label": "어휘와 표현",
        "feedback": "기본 단어로 내용을 잘 표현했지만, 몇몇 표현은 더 자연스럽게 바꿀 수 있습니다.",
        "example": "예: \"didn't attention\" 대신 \"was not paying attention\"을 쓰면 자연스럽습니다."
      },
      {
        "key": "grammarAccuracy",
        "label": "문법 정확성",
        "feedback": "관사, 시제, 복수형을 조금 더 정확히 쓰는 연습이 필요합니다. 이런 부분만 고치면 글이 훨씬 좋아집니다.",
        "example": "예: \"a real dog\", \"were practicing\", \"the dog saved all the fish\"처럼 써 보세요."
      }
    ]
  },
  "strengths": {
    "items": [
      "이야기의 핵심 사건과 결말을 빠뜨리지 않고 잘 전달했습니다.",
      "원인과 결과를 연결해서 설명하려는 시도가 좋았습니다."
    ]
  },
  "areasToImprove": {
    "items": [
      "자주 쓰는 표현을 문장 덩어리로 익히세요: pay attention to, spill into, save the fish.",
      "긴 문장을 두세 문장으로 나누고, 관사(a/the)와 시제(was/were + ing, saved)를 꼭 확인하세요."
    ]
  }
}